{
	"info": {
		"_postman_id": "a85872e8-a594-47f9-bf7c-f914505713d0",
		"name": "Finance",
		"schema": "https://schema.getpostman.com/json/collection/v2.1.0/collection.json",
		"_exporter_id": "9721190"
	},
	"item": [
		{
			"name": "User",
			"item": [
				{
					"name": "Create",
					"event": [
						{
							"listen": "test",
							"script": {
								"exec": [
									"var data = pm.response.json();\r",
									"\r",
									"pm.environment.set(\"token\", data.token.accessToken);\r",
									"pm.environment.set(\"user_id\", data.user.id);"
								],
								"type": "text/javascript"
							}
						}
					],
					"request": {
						"method": "POST",
						"header": [],
						"body": {
							"mode": "raw",
							"raw": "{\r\n    \"email\" : \"bartukocakara@gmail.com\",\r\n    \"deviceID\" : \"1231313\",\r\n    \"password\" : \"123456\"\r\n}",
							"options": {
								"raw": {
									"language": "json"
								}
							}
						},
						"url": {
							"raw": "{{base_url}}/api/v1/users",
							"host": [
								"{{base_url}}"
							],
							"path": [
								"api",
								"v1",
								"users"
							]
						}
					},
					"response": []
				},
				{
					"name": "List",
					"request": {
						"auth": {
							"type": "bearer",
							"bearer": [
								{
									"key": "token",
									"value": "{{token}}",
									"type": "string"
								}
							]
						},
						"method": "GET",
						"header": [],
						"url": {
							"raw": "{{base_url}}/api/v1/users",
							"host": [
								"{{base_url}}"
							],
							"path": [
								"api",
								"v1",
								"users"
							]
						}
					},
					"response": []
				},
				{
					"name": "Get",
					"request": {
						"auth": {
							"type": "bearer",
							"bearer": [
								{
									"key": "token",
									"value": "{{token}}",
									"type": "string"
								}
							]
						},
						"method": "GET",
						"header": [],
						"url": {
							"raw": "{{base_url}}/api/v1/users/{{user_id}}",
							"host": [
								"{{base_url}}"
							],
							"path": [
								"api",
								"v1",
								"users",
								"{{user_id}}"
							]
						}
					},
					"response": []
				},
				{
					"name": "Update User",
					"request": {
						"auth": {
							"type": "bearer",
							"bearer": [
								{
									"key": "token",
									"value": "{{token}}",
									"type": "string"
								}
							]
						},
						"method": "PATCH",
						"header": [],
						"body": {
							"mode": "raw",
							"raw": "{\r\n    \"email\": \"kocakarabartu@gmail.com\",\r\n    \"password\": \"12345\"\r\n}",
							"options": {
								"raw": {
									"language": "json"
								}
							}
						},
						"url": {
							"raw": "{{base_url}}/api/v1/users/{{user_id}}",
							"host": [
								"{{base_url}}"
							],
							"path": [
								"api",
								"v1",
								"users",
								"{{user_id}}"
							]
						}
					},
					"response": []
				},
				{
					"name": "Delete",
					"request": {
						"auth": {
							"type": "bearer",
							"bearer": [
								{
									"key": "token",
									"value": "{{token}}",
									"type": "string"
								}
							]
						},
						"method": "DELETE",
						"header": [],
						"url": {
							"raw": "{{base_url}}/api/v1/users/{{user_id}}",
							"host": [
								"{{base_url}}"
							],
							"path": [
								"api",
								"v1",
								"users",
								"{{user_id}}"
							]
						}
					},
					"response": []
				}
			]
		},
		{
			"name": "Auth",
			"item": [
				{
					"name": "Login",
					"event": [
						{
							"listen": "test",
							"script": {
								"exec": [
									"var data = pm.response.json();\r",
									"\r",
									"pm.environment.set(\"token\", data.token.accessToken);\r",
									"pm.environment.set(\"user_id\", data.user.id);"
								],
								"type": "text/javascript"
							}
						}
					],
					"request": {
						"method": "POST",
						"header": [],
						"body": {
							"mode": "raw",
							"raw": "{\r\n    \"email\" : \"bartukocakara@gmail.com\",\r\n    \"deviceID\" : \"12345\",\r\n    \"password\" : \"123456\"\r\n}",
							"options": {
								"raw": {
									"language": "json"
								}
							}
						},
						"url": {
							"raw": "{{base_url}}/api/v1/login",
							"host": [
								"{{base_url}}"
							],
							"path": [
								"api",
								"v1",
								"login"
							]
						}
					},
					"response": []
				}
			]
		},
		{
			"name": "User Role",
			"item": [
				{
					"name": "Create",
					"request": {
						"auth": {
							"type": "bearer",
							"bearer": [
								{
									"key": "token",
									"value": "{{token}}",
									"type": "string"
								}
							]
						},
						"method": "POST",
						"header": [],
						"body": {
							"mode": "raw",
							"raw": "{\r\n    \"role\" : \"user\"\r\n}",
							"options": {
								"raw": {
									"language": "json"
								}
							}
						},
						"url": {
							"raw": "{{base_url}}/api/v1/users/{{user_id}}/roles",
							"host": [
								"{{base_url}}"
							],
							"path": [
								"api",
								"v1",
								"users",
								"{{user_id}}",
								"roles"
							]
						}
					},
					"response": []
				},
				{
					"name": "Delete",
					"request": {
						"auth": {
							"type": "bearer",
							"bearer": [
								{
									"key": "token",
									"value": "{{token}}",
									"type": "string"
								}
							]
						},
						"method": "DELETE",
						"header": [],
						"body": {
							"mode": "raw",
							"raw": "{\r\n    \"role\" : \"admin\"\r\n}",
							"options": {
								"raw": {
									"language": "json"
								}
							}
						},
						"url": {
							"raw": "{{base_url}}/api/v1/users/{{user_id}}/roles",
							"host": [
								"{{base_url}}"
							],
							"path": [
								"api",
								"v1",
								"users",
								"{{user_id}}",
								"roles"
							]
						}
					},
					"response": []
				},
				{
					"name": "List",
					"request": {
						"auth": {
							"type": "bearer",
							"bearer": [
								{
									"key": "token",
									"value": "{{token}}",
									"type": "string"
								}
							]
						},
						"method": "GET",
						"header": [],
						"url": {
							"raw": "{{base_url}}/api/v1/users/{{user_id}}/roles",
							"host": [
								"{{base_url}}"
							],
							"path": [
								"api",
								"v1",
								"users",
								"{{user_id}}",
								"roles"
							]
						}
					},
					"response": []
				},
				{
					"name": "Update",
					"request": {
						"auth": {
							"type": "bearer",
							"bearer": [
								{
									"key": "token",
									"value": "{{token}}",
									"type": "string"
								}
							]
						},
						"method": "PUT",
						"header": [],
						"body": {
							"mode": "raw",
							"raw": "{\r\n    \"role\" : \"user\"\r\n}",
							"options": {
								"raw": {
									"language": "json"
								}
							}
						},
						"url": {
							"raw": "{{base_url}}/api/v1/users/{{user_id}}/roles",
							"host": [
								"{{base_url}}"
							],
							"path": [
								"api",
								"v1",
								"users",
								"{{user_id}}",
								"roles"
							]
						}
					},
					"response": []
				}
			]
		},
		{
			"name": "Account",
			"item": [
				{
					"name": "Create",
					"request": {
						"auth": {
							"type": "bearer",
							"bearer": [
								{
									"key": "token",
									"value": "{{token}}",
									"type": "string"
								}
							]
						},
						"method": "POST",
						"header": [],
						"body": {
							"mode": "raw",
							"raw": "{\r\n    \"account_name\" : \"bartukocakara\",\r\n    \"type\" : \"cash\",\r\n    \"start_balance\" : 200,\r\n    \"currency\" : \"TL\"\r\n}",
							"options": {
								"raw": {
									"language": "json"
								}
							}
						},
						"url": {
							"raw": "{{base_url}}/api/v1/users/{{user_id}}/accounts",
							"host": [
								"{{base_url}}"
							],
							"path": [
								"api",
								"v1",
								"users",
								"{{user_id}}",
								"accounts"
							]
						}
					},
					"response": []
				},
				{
					"name": "List",
					"event": [
						{
							"listen": "test",
							"script": {
								"exec": [
									"    var jsonData = pm.response.json();\r",
									"    console.log(jsonData)\r",
									"\r",
									"pm.environment.set(\"account_id\", jsonData[0].id);"
								],
								"type": "text/javascript"
							}
						}
					],
					"request": {
						"auth": {
							"type": "bearer",
							"bearer": [
								{
									"key": "token",
									"value": "{{token}}",
									"type": "string"
								}
							]
						},
						"method": "GET",
						"header": [],
						"url": {
							"raw": "{{base_url}}/api/v1/users/{{user_id}}/accounts",
							"host": [
								"{{base_url}}"
							],
							"path": [
								"api",
								"v1",
								"users",
								"{{user_id}}",
								"accounts"
							]
						}
					},
					"response": []
				},
				{
					"name": "Patch",
					"request": {
						"auth": {
							"type": "bearer",
							"bearer": [
								{
									"key": "token",
									"value": "{{token}}",
									"type": "string"
								}
							]
						},
						"method": "PATCH",
						"header": [],
						"body": {
							"mode": "raw",
							"raw": "{\r\n    \"account_name\" : \"my account\",\r\n    \"type\" : \"cash\",\r\n    \"startBalance\" : 1000,\r\n    \"currency\" : \"EU\"\r\n}",
							"options": {
								"raw": {
									"language": "json"
								}
							}
						},
						"url": {
							"raw": "{{base_url}}/api/v1/users/{{user_id}}/accounts/{{account_id}}",
							"host": [
								"{{base_url}}"
							],
							"path": [
								"api",
								"v1",
								"users",
								"{{user_id}}",
								"accounts",
								"{{account_id}}"
							]
						}
					},
					"response": []
				},
				{
					"name": "Show",
					"request": {
						"auth": {
							"type": "bearer",
							"bearer": [
								{
									"key": "token",
									"value": "{{token}}",
									"type": "string"
								}
							]
						},
						"method": "GET",
						"header": [],
						"url": {
							"raw": "{{base_url}}/api/v1/users/{{user_id}}/accounts/{{account_id}}",
							"host": [
								"{{base_url}}"
							],
							"path": [
								"api",
								"v1",
								"users",
								"{{user_id}}",
								"accounts",
								"{{account_id}}"
							]
						}
					},
					"response": []
				},
				{
					"name": "Delete",
					"request": {
						"auth": {
							"type": "bearer",
							"bearer": [
								{
									"key": "token",
									"value": "{{token}}",
									"type": "string"
								}
							]
						},
						"method": "DELETE",
						"header": [],
						"url": {
							"raw": "{{base_url}}/api/v1/users/{{user_id}}/accounts/{{account_id}}",
							"host": [
								"{{base_url}}"
							],
							"path": [
								"api",
								"v1",
								"users",
								"{{user_id}}",
								"accounts",
								"{{account_id}}"
							]
						}
					},
					"response": []
				}
			]
		},
		{
			"name": "Category",
			"item": [
				{
					"name": "Create",
					"request": {
						"auth": {
							"type": "bearer",
							"bearer": [
								{
									"key": "token",
									"value": "{{token}}",
									"type": "string"
								}
							]
						},
						"method": "POST",
						"header": [],
						"body": {
							"mode": "raw",
							"raw": "{\r\n    \"name\" : \"payment\"\r\n}",
							"options": {
								"raw": {
									"language": "json"
								}
							}
						},
						"url": {
							"raw": "{{base_url}}/api/v1/users/{{user_id}}/categories",
							"host": [
								"{{base_url}}"
							],
							"path": [
								"api",
								"v1",
								"users",
								"{{user_id}}",
								"categories"
							]
						}
					},
					"response": []
				},
				{
					"name": "List",
					"event": [
						{
							"listen": "test",
							"script": {
								"exec": [
									"    var jsonData = pm.response.json();\r",
									"    console.log(jsonData)\r",
									"\r",
									"pm.environment.set(\"category_id\", jsonData[0].id);"
								],
								"type": "text/javascript"
							}
						}
					],
					"request": {
						"auth": {
							"type": "bearer",
							"bearer": [
								{
									"key": "token",
									"value": "{{token}}",
									"type": "string"
								}
							]
						},
						"method": "GET",
						"header": [],
						"url": {
							"raw": "{{base_url}}/api/v1/users/{{user_id}}/categories",
							"host": [
								"{{base_url}}"
							],
							"path": [
								"api",
								"v1",
								"users",
								"{{user_id}}",
								"categories"
							]
						}
					},
					"response": []
				},
				{
					"name": "Update",
					"request": {
						"auth": {
							"type": "bearer",
							"bearer": [
								{
									"key": "token",
									"value": "{{token}}",
									"type": "string"
								}
							]
						},
						"method": "PATCH",
						"header": [],
						"body": {
							"mode": "raw",
							"raw": "{\r\n    \"name\" : \"work\"\r\n}",
							"options": {
								"raw": {
									"language": "json"
								}
							}
						},
						"url": {
							"raw": "{{base_url}}/api/v1/users/{{user_id}}/categories/{{category_id}}",
							"host": [
								"{{base_url}}"
							],
							"path": [
								"api",
								"v1",
								"users",
								"{{user_id}}",
								"categories",
								"{{category_id}}"
							]
						}
					},
					"response": []
				},
				{
					"name": "Show",
					"request": {
						"auth": {
							"type": "bearer",
							"bearer": [
								{
									"key": "token",
									"value": "{{token}}",
									"type": "string"
								}
							]
						},
						"method": "GET",
						"header": [],
						"url": {
							"raw": "{{base_url}}/api/v1/users/{{user_id}}/categories/{{category_id}}",
							"host": [
								"{{base_url}}"
							],
							"path": [
								"api",
								"v1",
								"users",
								"{{user_id}}",
								"categories",
								"{{category_id}}"
							]
						}
					},
					"response": []
				},
				{
					"name": "Delete",
					"request": {
						"auth": {
							"type": "bearer",
							"bearer": [
								{
									"key": "token",
									"value": "{{token}}",
									"type": "string"
								}
							]
						},
						"method": "DELETE",
						"header": [],
						"url": {
							"raw": "{{base_url}}/api/v1/users/{{user_id}}/categories/{{category_id}}",
							"host": [
								"{{base_url}}"
							],
							"path": [
								"api",
								"v1",
								"users",
								"{{user_id}}",
								"categories",
								"{{category_id}}"
							]
						}
					},
					"response": []
				}
			]
		},
		{
			"name": "Merchant",
			"item": [
				{
					"name": "Create",
					"request": {
						"auth": {
							"type": "bearer",
							"bearer": [
								{
									"key": "token",
									"value": "{{token}}",
									"type": "string"
								}
							]
						},
						"method": "POST",
						"header": [],
						"body": {
							"mode": "raw",
							"raw": "{\r\n    \"name\" : \"Merchant Bartu PL\"\r\n}",
							"options": {
								"raw": {
									"language": "json"
								}
							}
						},
						"url": {
							"raw": "{{base_url}}/api/v1/users/{{user_id}}/merchants",
							"host": [
								"{{base_url}}"
							],
							"path": [
								"api",
								"v1",
								"users",
								"{{user_id}}",
								"merchants"
							]
						}
					},
					"response": []
				},
				{
					"name": "List",
					"event": [
						{
							"listen": "test",
							"script": {
								"exec": [
									"    var jsonData = pm.response.json();\r",
									"    console.log(jsonData)\r",
									"\r",
									"pm.environment.set(\"merchant_id\", jsonData[0].id);"
								],
								"type": "text/javascript"
							}
						}
					],
					"protocolProfileBehavior": {
						"disableBodyPruning": true
					},
					"request": {
						"auth": {
							"type": "bearer",
							"bearer": [
								{
									"key": "token",
									"value": "{{token}}",
									"type": "string"
								}
							]
						},
						"method": "GET",
						"header": [],
						"body": {
							"mode": "raw",
							"raw": "",
							"options": {
								"raw": {
									"language": "json"
								}
							}
						},
						"url": {
							"raw": "{{base_url}}/api/v1/users/{{user_id}}/merchants",
							"host": [
								"{{base_url}}"
							],
							"path": [
								"api",
								"v1",
								"users",
								"{{user_id}}",
								"merchants"
							]
						}
					},
					"response": []
				},
				{
					"name": "Show",
					"protocolProfileBehavior": {
						"disableBodyPruning": true
					},
					"request": {
						"auth": {
							"type": "bearer",
							"bearer": [
								{
									"key": "token",
									"value": "eyJhbGciOiJIUzUxMiIsInR5cCI6IkpXVCJ9.eyJ1c2VySUQiOiI4ZjI2NGFmNi1iMzA1LTRkODMtYjc5Mi05NzFkYmJhY2FkMjIiLCJleHAiOjE2NTc0ODU1MjIsImlhdCI6MTY1NDg5MzUyMn0.ImP_6puKS7h-WyEoUtd-0Uzbe_l893eguNUYBnT6Tpsr2ZdtNwFAGnigpCALUjgCw_0z2QoAMlMdl1re5Rn3mg",
									"type": "string"
								}
							]
						},
						"method": "GET",
						"header": [],
						"body": {
							"mode": "raw",
							"raw": "{\r\n    \"name\" : \"payment\"\r\n}",
							"options": {
								"raw": {
									"language": "json"
								}
							}
						},
						"url": {
							"raw": "{{base_url}}/api/v1/users/{{user_id}}/merchants/6e3b579a-fb1b-4111-8f66-64e1f7d21cfa",
							"host": [
								"{{base_url}}"
							],
							"path": [
								"api",
								"v1",
								"users",
								"{{user_id}}",
								"merchants",
								"6e3b579a-fb1b-4111-8f66-64e1f7d21cfa"
							]
						}
					},
					"response": []
				},
				{
					"name": "Patch",
					"request": {
						"auth": {
							"type": "bearer",
							"bearer": [
								{
									"key": "token",
									"value": "{{token}}",
									"type": "string"
								}
							]
						},
						"method": "PATCH",
						"header": [],
						"body": {
							"mode": "raw",
							"raw": "{\r\n    \"name\" : \"Bartu Kocakara GER\"\r\n}",
							"options": {
								"raw": {
									"language": "json"
								}
							}
						},
						"url": {
							"raw": "{{base_url}}/api/v1/users/{{user_id}}/merchants/{{merchant_id}}",
							"host": [
								"{{base_url}}"
							],
							"path": [
								"api",
								"v1",
								"users",
								"{{user_id}}",
								"merchants",
								"{{merchant_id}}"
							]
						}
					},
					"response": []
				},
				{
					"name": "Delete",
					"request": {
						"auth": {
							"type": "bearer",
							"bearer": [
								{
									"key": "token",
									"value": "{{token}}",
									"type": "string"
								}
							]
						},
						"method": "DELETE",
						"header": [],
						"body": {
							"mode": "raw",
							"raw": "",
							"options": {
								"raw": {
									"language": "json"
								}
							}
						},
						"url": {
							"raw": "{{base_url}}/api/v1/users/{{user_id}}/merchants/{{merchant_id}}",
							"host": [
								"{{base_url}}"
							],
							"path": [
								"api",
								"v1",
								"users",
								"{{user_id}}",
								"merchants",
								"{{merchant_id}}"
							]
						}
					},
					"response": []
				}
			]
		},
		{
			"name": "Transaction",
			"item": [
				{
					"name": "List By Category",
					"event": [
						{
							"listen": "test",
							"script": {
								"exec": [
									"    var jsonData = pm.response.json();\r",
									"    console.log(jsonData)\r",
									"\r",
									"pm.environment.set(\"transaction_id\", jsonData[0].id);"
								],
								"type": "text/javascript"
							}
						}
					],
					"request": {
						"auth": {
							"type": "bearer",
							"bearer": [
								{
									"key": "token",
									"value": "{{token}}",
									"type": "string"
								}
							]
						},
						"method": "GET",
						"header": [],
						"url": {
							"raw": "{{base_url}}/api/v1/categories/{{category_id}}/transactions?to=2023-01-02T15:04:05Z&from=2006-01-02T15:04:05Z&limit=10",
							"host": [
								"{{base_url}}"
							],
							"path": [
								"api",
								"v1",
								"categories",
								"{{category_id}}",
								"transactions"
							],
							"query": [
								{
									"key": "to",
									"value": "2023-01-02T15:04:05Z"
								},
								{
									"key": "from",
									"value": "2006-01-02T15:04:05Z"
								},
								{
									"key": "limit",
									"value": "10"
								}
							]
						}
					},
					"response": []
				},
				{
					"name": "List By User",
					"event": [
						{
							"listen": "test",
							"script": {
								"exec": [
									"    var jsonData = pm.response.json();\r",
									"    console.log(jsonData)\r",
									"\r",
									"pm.environment.set(\"transaction_id\", jsonData[0].id);"
								],
								"type": "text/javascript"
							}
						}
					],
					"request": {
						"auth": {
							"type": "bearer",
							"bearer": [
								{
									"key": "token",
									"value": "{{token}}",
									"type": "string"
								}
							]
						},
						"method": "GET",
						"header": [],
						"url": {
							"raw": "{{base_url}}/api/v1/users/{{user_id}}/transactions?from=2006-01-02T15:04:05Z&to=2023-01-02T15:04:05Z&limit=10",
							"host": [
								"{{base_url}}"
							],
							"path": [
								"api",
								"v1",
								"users",
								"{{user_id}}",
								"transactions"
							],
							"query": [
								{
									"key": "from",
									"value": "2006-01-02T15:04:05Z"
								},
								{
									"key": "to",
									"value": "2023-01-02T15:04:05Z"
								},
								{
									"key": "limit",
									"value": "10"
								}
							]
						}
					},
					"response": []
				},
				{
					"name": "List By Account",
					"request": {
						"auth": {
							"type": "bearer",
							"bearer": [
								{
									"key": "token",
									"value": "{{token}}",
									"type": "string"
								}
							]
						},
						"method": "GET",
						"header": [],
						"url": {
							"raw": "{{base_url}}/api/v1/accounts/{{account_id}}/transactions?from=2006-01-02T15:04:05Z&to=2023-01-02T15:04:05Z",
							"host": [
								"{{base_url}}"
							],
							"path": [
								"api",
								"v1",
								"accounts",
								"{{account_id}}",
								"transactions"
							],
							"query": [
								{
									"key": "from",
									"value": "2006-01-02T15:04:05Z"
								},
								{
									"key": "to",
									"value": "2023-01-02T15:04:05Z"
								}
							]
						}
					},
					"response": []
				},
				{
					"name": "List All",
					"request": {
						"auth": {
							"type": "bearer",
							"bearer": [
								{
									"key": "token",
									"value": "{{token}}",
									"type": "string"
								}
							]
						},
						"method": "GET",
						"header": [],
						"url": {
							"raw": "{{base_url}}/api/v1/transactions?from=2006-01-02T15:04:05Z&to=2023-01-02T15:04:05Z&limit=10",
							"host": [
								"{{base_url}}"
							],
							"path": [
								"api",
								"v1",
								"transactions"
							],
							"query": [
								{
									"key": "from",
									"value": "2006-01-02T15:04:05Z"
								},
								{
									"key": "to",
									"value": "2023-01-02T15:04:05Z"
								},
								{
									"key": "limit",
									"value": "10"
								}
							]
						}
					},
					"response": []
				},
				{
					"name": "Create",
					"request": {
						"auth": {
							"type": "bearer",
							"bearer": [
								{
									"key": "token",
									"value": "{{token}}",
									"type": "string"
								}
							]
						},
						"method": "POST",
						"header": [],
						"body": {
							"mode": "raw",
							"raw": "{\r\n    \"account_id\" : \"{{account_id}}\",\r\n    \"category_id\" : \"{{category_id}}\",\r\n    \"type\" :  \"expense\",\r\n    \"amount\" : 10000,\r\n    \"currency\" : \"USD\",\r\n    \"notes\" : \"Holiday payment\"\r\n}",
							"options": {
								"raw": {
									"language": "json"
								}
							}
						},
						"url": {
							"raw": "{{base_url}}/api/v1/users/{{user_id}}/transactions",
							"host": [
								"{{base_url}}"
							],
							"path": [
								"api",
								"v1",
								"users",
								"{{user_id}}",
								"transactions"
							]
						}
					},
					"response": []
				},
				{
					"name": "Update",
					"request": {
						"auth": {
							"type": "bearer",
							"bearer": [
								{
									"key": "token",
									"value": "{{token}}",
									"type": "string"
								}
							]
						},
						"method": "PATCH",
						"header": [],
						"body": {
							"mode": "raw",
							"raw": "{\r\n    \"account_id\" : \"{{account_id}}\",\r\n    \"category_id\" : \"{{category_id}}\",\r\n    \"type\" : \"expense\",\r\n    \"date\" : \"2023-01-02T15:04:05Z\",\r\n    \"currency\" : \"USD\",\r\n    \"amount\" : 12000\r\n}",
							"options": {
								"raw": {
									"language": "json"
								}
							}
						},
						"url": {
							"raw": "{{base_url}}/api/v1/users/{{user_id}}/transactions/{{transaction_id}}",
							"host": [
								"{{base_url}}"
							],
							"path": [
								"api",
								"v1",
								"users",
								"{{user_id}}",
								"transactions",
								"{{transaction_id}}"
							]
						}
					},
					"response": []
				},
				{
					"name": "Show By UserID",
					"request": {
						"auth": {
							"type": "bearer",
							"bearer": [
								{
									"key": "token",
									"value": "eyJhbGciOiJIUzUxMiIsInR5cCI6IkpXVCJ9.eyJ1c2VySUQiOiI4ZjI2NGFmNi1iMzA1LTRkODMtYjc5Mi05NzFkYmJhY2FkMjIiLCJleHAiOjE2NTc0ODU1MjIsImlhdCI6MTY1NDg5MzUyMn0.ImP_6puKS7h-WyEoUtd-0Uzbe_l893eguNUYBnT6Tpsr2ZdtNwFAGnigpCALUjgCw_0z2QoAMlMdl1re5Rn3mg",
									"type": "string"
								}
							]
						},
						"method": "GET",
						"header": [],
						"url": {
							"raw": "{{base_url}}/api/v1/users/{{user_id}}/transactions/{{transaction_id}}",
							"host": [
								"{{base_url}}"
							],
							"path": [
								"api",
								"v1",
								"users",
								"{{user_id}}",
								"transactions",
								"{{transaction_id}}"
							]
						}
					},
					"response": []
				},
				{
					"name": "Show By ID",
					"request": {
						"auth": {
							"type": "bearer",
							"bearer": [
								{
									"key": "token",
									"value": "{{token}}",
									"type": "string"
								}
							]
						},
						"method": "GET",
						"header": [],
						"url": {
							"raw": "{{base_url}}/api/v1/transactions/{{transaction_id}}",
							"host": [
								"{{base_url}}"
							],
							"path": [
								"api",
								"v1",
								"transactions",
								"{{transaction_id}}"
							]
						}
					},
					"response": []
				},
				{
					"name": "Delete",
					"request": {
						"auth": {
							"type": "bearer",
							"bearer": [
								{
									"key": "token",
									"value": "{{token}}",
									"type": "string"
								}
							]
						},
						"method": "DELETE",
						"header": [],
						"url": {
							"raw": "{{base_url}}/api/v1/users/{{user_id}}/transactions/{{transaction_id}}",
							"host": [
								"{{base_url}}"
							],
							"path": [
								"api",
								"v1",
								"users",
								"{{user_id}}",
								"transactions",
								"{{transaction_id}}"
							]
						}
					},
					"response": []
				}
			]
		},
		{
			"name": "Version",
			"protocolProfileBehavior": {
				"disableBodyPruning": true
			},
			"request": {
				"method": "GET",
				"header": [],
				"body": {
					"mode": "raw",
					"raw": "{\r\n    \"email\" : \"kocakaabartu@gmai.com\",\r\n    \"password\" : \"1234567\"\r\n}",
					"options": {
						"raw": {
							"language": "json"
						}
					}
				},
				"url": {
					"raw": "{{base_url}}/version",
					"host": [
						"{{base_url}}"
					],
					"path": [
						"version"
					]
				}
			},
			"response": []
		}
	]
}